{
  "version": "2026.04.BB8.SIT",
  "generated_at": "2026-04-07T11:39:58Z",
  "commits": [
    {
      "author": "GitHub Action",
      "message": "Update daily commits data []",
      "timestamp": "2026-02-24T06:19:19Z"
    },
    {
      "author": "Nathi2266",
      "message": "feat: update asset paths and implement light/dark mode support across multiple screens",
      "timestamp": "2026-03-26T09:59:41+02:00"
    },
    {
      "author": "Thembelihle",
      "message": "Feature -  Add functionality for starting 1:1 meetings with admins and update alert action routes based on user role.",
      "timestamp": "2026-04-07T13:39:14+02:00"
    },
    {
      "author": "Thembelihle",
      "message": "Feature -  Enhance alert filtering logic and update user alerts stream to support customizable item limits.",
      "timestamp": "2026-04-07T13:23:21+02:00"
    },
    {
      "author": "Thembelihle",
      "message": "Feature -  Clean up color getter methods and improve code formatting in alerts_nudges_screen.dart",
      "timestamp": "2026-04-07T13:12:27+02:00"
    },
    {
      "author": "Thembelihle",
      "message": "Feature - Refactor alert handling for goal approvals and rejections.",
      "timestamp": "2026-04-07T12:54:08+02:00"
    },
    {
      "author": "BhutSipho",
      "message": "Feat: Status Badges Implement For Goals",
      "timestamp": "2026-04-07T11:56:26+02:00"
    },
    {
      "author": "BhutSipho",
      "message": "Feat:Enable Navigation from PDP Goals to Milestone Details",
      "timestamp": "2026-04-07T10:46:18+02:00"
    }
  ],
  "total_commits": 8,
  "date_range": "2026-04-07"
}
