{
  "version": "2026.03.DB4.SIT",
  "generated_at": "2026-03-17T07:48:39Z",
  "commits": [
    {
      "author": "GitHub Action",
      "message": "Update daily commits data []",
      "timestamp": "2026-02-24T06:19:19Z"
    },
    {
      "author": "Thembelihle",
      "message": "Feature - Enhance team progress visuals by adding fallback trend generation, current period calculations.",
      "timestamp": "2026-03-10T11:52:29+02:00"
    },
    {
      "author": "BhutSipho",
      "message": "🔧 Implement unified Firestore stream broker to fix INTERNAL ASSERTION FAILED errors",
      "timestamp": "2026-03-17T07:53:27+02:00"
    },
    {
      "author": "Nathi2266",
      "message": "dropdown icon added for the chatbot and chat button",
      "timestamp": "2026-03-17T15:44:38+02:00"
    },
    {
      "author": "Thembelihle",
      "message": "Feature - implement goal approval inbox card with fallback handling",
      "timestamp": "2026-03-17T14:34:32+02:00"
    },
    {
      "author": "Nathi2266",
      "message": "refactor: replace Admin screens with shared components for improved consistency and maintainability",
      "timestamp": "2026-03-17T09:44:24+02:00"
    },
    {
      "author": "Nathi2266",
      "message": "feat: implement Manager Goal Workspace menu with updated routing and sidebar configuration",
      "timestamp": "2026-03-17T07:29:16+02:00"
    }
  ],
  "total_commits": 4,
  "date_range": "2026-03-17"
}
